pyiron_workflow_lammps/__init__.py
pyiron_workflow_lammps/_version.py
pyiron_workflow_lammps/dataclass_storage.py
pyiron_workflow_lammps/engine.py
pyiron_workflow_lammps/generic.py
pyiron_workflow_lammps/lammps.py
pyiron_workflow_lammps-0.0.2.dist-info/licenses/LICENSE
pyiron_workflow_lammps-0.0.2.dist-info/METADATA
pyiron_workflow_lammps-0.0.2.dist-info/WHEEL
pyiron_workflow_lammps-0.0.2.dist-info/top_level.txt
pyiron_workflow_lammps-0.0.2.dist-info/RECORD
