Metadata-Version: 2.4
Name: pyiron_workflow_lammps
Version: 0.0.2
Summary: A LAMMPS workflow integration package for pyiron
Author-email: pyiron Team <pyiron@mpie.de>
License: BSD 3-Clause License
Project-URL: Homepage, https://github.com/pyiron/pyiron_workflow_lammps
Project-URL: Documentation, https://github.com/pyiron/pyiron_workflow_lammps
Project-URL: Repository, https://github.com/pyiron/pyiron_workflow_lammps
Project-URL: Bug Tracker, https://github.com/pyiron/pyiron_workflow_lammps/issues
Keywords: pyiron,lammps,workflow,molecular-dynamics,materials-science
Classifier: Development Status :: 4 - Beta
Classifier: Topic :: Scientific/Engineering
Classifier: License :: OSI Approved :: BSD License
Classifier: Intended Audience :: Science/Research
Classifier: Operating System :: OS Independent
Classifier: Programming Language :: Python :: 3.10
Classifier: Programming Language :: Python :: 3.11
Classifier: Programming Language :: Python :: 3.12
Requires-Python: <3.13,>=3.11
License-File: LICENSE
Requires-Dist: numpy<1.27.0,>=1.26.4
Requires-Dist: pandas<2.4.0,>=2.2.3
Requires-Dist: pyiron-workflow<=0.15.2,>=0.14.0
Requires-Dist: pyiron-workflow-atomistics==0.0.2
Requires-Dist: pyiron-lammps==0.4.6
Requires-Dist: ase<3.27.0,>=3.22.1
Requires-Dist: pymatgen<2025.7.0,>=2024.8.8
Provides-Extra: dev
Requires-Dist: pytest>=6.0; extra == "dev"
Requires-Dist: pytest-cov>=2.0; extra == "dev"
Requires-Dist: black>=22.0; extra == "dev"
Requires-Dist: isort>=5.0; extra == "dev"
Requires-Dist: ruff>=0.5; extra == "dev"
Provides-Extra: notebook
Requires-Dist: jupyter>=1.0.0; extra == "notebook"
Requires-Dist: notebook>=6.0.0; extra == "notebook"
Provides-Extra: cluster
Requires-Dist: pysqa==0.3.0; extra == "cluster"
Requires-Dist: h5py==3.14.0; extra == "cluster"
Dynamic: license-file
